{
  "batch_summary": {
    "total_cdr_rows": 7,
    "valid_cdr_rows": 7,
    "malformed_cdr_rows": 0,
    "total_billed_cost": 915.5
  },
  "subscribers": {
    "9800011122": {
      "plan_type": "postpaid",
      "call_count": 2,
      "total_cost": 63.0
    },
    "9812345678": {
      "plan_type": "prepaid",
      "call_count": 2,
      "total_cost": 8.0
    },
    "9876543210": {
      "plan_type": "postpaid",
      "call_count": 2,
      "total_cost": 844.5
    }
  },
  "anomalies": {
    "unknown_subscribers": [
      "9999999999"
    ],
    "unknown_subscriber_calls": [
      {
        "msisdn": "9999999999",
        "call_type": "domestic",
        "duration_sec": 120,
        "cost": 3.0
      }
    ],
    "suspicious_calls": [
      {
        "msisdn": "9876543210",
        "call_type": "international",
        "duration_sec": 4200,
        "cost": 840.0
      }
    ]
  }
}
